README.md
setup.cfg
setup.py
pywinter/KreatE_inter_m_f.f90
pywinter/__init__.py
pywinter/winter.py
pywinter.egg-info/PKG-INFO
pywinter.egg-info/SOURCES.txt
pywinter.egg-info/dependency_links.txt
pywinter.egg-info/top_level.txt