Metadata-Version: 1.2
Name: pywinter
Version: 2.0.5
Summary: Read and Create WRF-WPS intermediate files
Home-page: https://github.com/dniloash/Pywinter
Author: Danilo A Suarez H
Author-email: dniloash@gmail.com
License: UNKNOWN
Download-URL: https://github.com/dniloash/Pywinter/tarball/2.0.5
Keywords: Python,WRF,WPS,Intermediate files
Platform: UNKNOWN
Requires-Python: >=3.6
